pytest_gevent.py
pytest_gevent-1.1.0.dist-info/LICENSE
pytest_gevent-1.1.0.dist-info/METADATA
pytest_gevent-1.1.0.dist-info/WHEEL
pytest_gevent-1.1.0.dist-info/entry_points.txt
pytest_gevent-1.1.0.dist-info/top_level.txt
pytest_gevent-1.1.0.dist-info/RECORD
