Metadata-Version: 2.1
Name: pytest-gevent
Version: 1.1.0
Summary: Ensure that gevent is properly patched when invoking pytest
Home-page: https://github.com/asottile/pytest-gevent
Author: Anthony Sottile
Author-email: asottile@umich.edu
License: MIT
Platform: UNKNOWN
Classifier: License :: OSI Approved :: MIT License
Classifier: Programming Language :: Python :: 3
Classifier: Programming Language :: Python :: 3 :: Only
Classifier: Programming Language :: Python :: 3.6
Classifier: Programming Language :: Python :: 3.7
Classifier: Programming Language :: Python :: 3.8
Requires-Python: >=3.6.1
Requires-Dist: gevent
Requires-Dist: pytest
